Covid19India/__init__.py
Covid19India/covid19india.py
Covid19India-0.0.5.dist-info/LICENSE
Covid19India-0.0.5.dist-info/METADATA
Covid19India-0.0.5.dist-info/WHEEL
Covid19India-0.0.5.dist-info/top_level.txt
Covid19India-0.0.5.dist-info/RECORD
