Metadata-Version: 2.1
Name: Covid19India
Version: 0.0.5
Summary: A Python3 Library to get India's Covid-19 Patient Count.
Home-page: https://github.com/suraj-deshmukh/Covid19India
Author: Suraj Deshmukh
Author-email: surajdeshmukh96@gmail.com
License: MIT LICENSE
Platform: UNKNOWN
Classifier: License :: OSI Approved :: MIT License
Classifier: Programming Language :: Python :: 3
Classifier: Programming Language :: Python :: 3.7
Requires-Python: >=3
Requires-Dist: requests
Requires-Dist: beautifulsoup4
